pipelines/__init__.py
pipelines/errors.py
pipelines/schema.py
pipelines/version.py
pipelines/agents/__init__.py
pipelines/agents/agent_step.py
pipelines/agents/base.py
pipelines/agents/types.py
pipelines/agents/memory/__init__.py
pipelines/agents/memory/base.py
pipelines/agents/memory/conversation_memory.py
pipelines/agents/memory/no_memory.py
pipelines/data_handler/__init__.py
pipelines/data_handler/dataset.py
pipelines/data_handler/inputs.py
pipelines/data_handler/predictions.py
pipelines/data_handler/processor.py
pipelines/data_handler/samples.py
pipelines/document_stores/__init__.py
pipelines/document_stores/base.py
pipelines/document_stores/elasticsearch.py
pipelines/document_stores/faiss.py
pipelines/document_stores/filter_utils.py
pipelines/document_stores/milvus2.py
pipelines/document_stores/sql.py
pipelines/document_stores/utils.py
pipelines/nodes/__init__.py
pipelines/nodes/base.py
pipelines/nodes/answer_extractor/__init__.py
pipelines/nodes/answer_extractor/answer_extractor.py
pipelines/nodes/answer_extractor/answer_extractor_preprocessor.py
pipelines/nodes/answer_extractor/qa_filter.py
pipelines/nodes/answer_extractor/qa_filter_postprocessor.py
pipelines/nodes/combine_documents/__init__.py
pipelines/nodes/combine_documents/base.py
pipelines/nodes/combine_documents/map_reduce.py
pipelines/nodes/combine_documents/reduce.py
pipelines/nodes/combine_documents/stuff.py
pipelines/nodes/document/__init__.py
pipelines/nodes/document/document_intelligence.py
pipelines/nodes/document/document_preprocessor.py
pipelines/nodes/file_classifier/__init__.py
pipelines/nodes/file_classifier/file_type.py
pipelines/nodes/file_converter/__init__.py
pipelines/nodes/file_converter/base.py
pipelines/nodes/file_converter/docx.py
pipelines/nodes/file_converter/image.py
pipelines/nodes/file_converter/markdown.py
pipelines/nodes/file_converter/pdf.py
pipelines/nodes/file_converter/txt.py
pipelines/nodes/llm/__init__.py
pipelines/nodes/llm/chatglm.py
pipelines/nodes/llm/ernie_bot.py
paddle_pipelines-0.6.2.dist-info/METADATA
paddle_pipelines-0.6.2.dist-info/WHEEL
paddle_pipelines-0.6.2.dist-info/top_level.txt
paddle_pipelines-0.6.2.dist-info/RECORD
