Metadata-Version: 2.1
Name: paddle-pipelines
Version: 0.6.2
Summary: Paddle-Pipelines: An End to End Natural Language Proceessing Development Kit Based on PaddleNLP
Home-page: https://github.com/PaddlePaddle/PaddleNLP
Author: PaddlePaddle Speech and Language Team
Author-email: paddlenlp@baidu.com
License: Apache 2.0
Platform: UNKNOWN
Classifier: Programming Language :: Python :: 3
Classifier: Programming Language :: Python :: 3.7
Classifier: Programming Language :: Python :: 3.8
Classifier: Programming Language :: Python :: 3.9
Classifier: Programming Language :: Python :: 3.10
Classifier: License :: OSI Approved :: Apache Software License
Classifier: Operating System :: OS Independent
Requires-Python: >=3.7
Requires-Dist: paddlenlp >=2.5.2
Requires-Dist: paddleocr ==2.6.1.3
Requires-Dist: pdf2image >1.14
Requires-Dist: requests
Requires-Dist: pydantic
Requires-Dist: mmh3
Requires-Dist: more-itertools
Requires-Dist: elasticsearch <=7.11,>=7.7
Requires-Dist: sqlalchemy <2,>=1.4.2
Requires-Dist: sqlalchemy-utils
Requires-Dist: langdetect
Requires-Dist: python-docx
Requires-Dist: nltk
Requires-Dist: pdfplumber
Requires-Dist: faiss-cpu >=1.7.2
Requires-Dist: opencv-python >=4.4
Requires-Dist: opencv-contrib-python-headless
Requires-Dist: click ==8.0
Requires-Dist: numba
Requires-Dist: pymilvus >=2.1
Requires-Dist: wordcloud ==1.8.2.2
Requires-Dist: boilerpy3
Requires-Dist: events
Requires-Dist: sseclient-py ==1.7.2
Requires-Dist: spacy
Requires-Dist: tritonclient[all]
Requires-Dist: typing-extensions ==4.5.0
Requires-Dist: aistudio-sdk
Requires-Dist: markdown
